git_browse/__init__.py
git_browse/bitbucket.py
git_browse/browse.py
git_browse/github.py
git_browse/gitlab.py
git_browse/godocs.py
git_browse/phabricator.py
git_browse/py.typed
git_browse/sourcegraph.py
git_browse/typedefs.py
git_browse-2.15.0.dist-info/licenses/LICENSE
git_browse-2.15.0.dist-info/METADATA
git_browse-2.15.0.dist-info/WHEEL
git_browse-2.15.0.dist-info/entry_points.txt
git_browse-2.15.0.dist-info/top_level.txt
git_browse-2.15.0.dist-info/RECORD
